Metadata-Version: 1.1
Name: roulette-russe
Version: 0.0.62
Summary: Library to write your scrapers hassle free.
Home-page: https://github.com/Homestr/roulette_russe
Author: Mohamed Amjad LASRI
Author-email: amjadepot@gmail.com
License: UNKNOWN
Keywords: SCRAPING,ROULETTE_RUSSE,CRAWLING
Platform: UNKNOWN
Classifier: Development Status :: 3 - Alpha
Classifier: Intended Audience :: Developers
Classifier: Topic :: Software Development
Classifier: License :: OSI Approved :: MIT License
Classifier: Programming Language :: Python :: 3.5
Classifier: Programming Language :: Python :: 3.6
